gulfofmexico/__init__.py
gulfofmexico/__main__.py
gulfofmexico/async_scheduler.py
gulfofmexico/base.py
gulfofmexico/builtin.py
gulfofmexico/constants.py
gulfofmexico/context.py
gulfofmexico/engine/__init__.py
gulfofmexico/engine/core.py
gulfofmexico/engine/evaluator.py
gulfofmexico/engine/handlers/__init__.py
gulfofmexico/engine/handlers/control_flow.py
gulfofmexico/engine/handlers/functions.py
gulfofmexico/engine/handlers/special.py
gulfofmexico/engine/handlers/variables.py
gulfofmexico/engine/namespace.py
gulfofmexico/graphics/__init__.py
gulfofmexico/graphics/canvas.py
gulfofmexico/graphics/colors.py
gulfofmexico/handlers.py
gulfofmexico/ide/__init__.py
gulfofmexico/ide/__main__.py
gulfofmexico/ide/app.py
gulfofmexico/ide/editor.py
gulfofmexico/ide/highlighter.py
gulfofmexico/ide/qt_compat.py
gulfofmexico/ide/runner.py
gulfofmexico/ide/web_ide.py
gulfofmexico/interpreter.py
gulfofmexico/language_config.py
gulfofmexico/language_runtime.py
gulfofmexico/plugin_system.py
gulfofmexico/plugins/__init__.py
gulfofmexico/plugins/example_custom_statement.py
gulfofmexico/plugins/example_math_utils.py
gulfofmexico/processor/__init__.py
gulfofmexico/processor/expression_tree.py
gulfofmexico/processor/lexer.py
gulfofmexico/processor/syntax_tree.py
gulfofmexico/repl.py
gulfofmexico/serialize.py
gulfofmexico/utils.py
gulfofmexico-0.1.4.dist-info/METADATA
gulfofmexico-0.1.4.dist-info/WHEEL
gulfofmexico-0.1.4.dist-info/entry_points.txt
gulfofmexico-0.1.4.dist-info/licenses/LICENSE
gulfofmexico-0.1.4.dist-info/RECORD
