Metadata-Version: 2.4
Name: gulfofmexico
Version: 0.1.4
Summary: Experimental interpreter based on Lu Wilson's (TodePond) Gulf of Mexico conceptual design - featuring probabilistic variables, negative indexing, and temporal lifetimes
License: MIT
License-File: LICENSE
Keywords: interpreter,esoteric,programming-language,language-construction,dsl
Author: James Temple
Author-email: james@honey-badger.org
Requires-Python: >=3.10,<3.14
Classifier: Development Status :: 3 - Alpha
Classifier: Intended Audience :: Developers
Classifier: Intended Audience :: Education
Classifier: License :: OSI Approved :: MIT License
Classifier: Operating System :: OS Independent
Classifier: Programming Language :: Python :: 3
Classifier: Programming Language :: Python :: 3.10
Classifier: Programming Language :: Python :: 3.11
Classifier: Programming Language :: Python :: 3.12
Classifier: Programming Language :: Python :: 3.13
Classifier: Topic :: Software Development :: Compilers
Classifier: Topic :: Software Development :: Interpreters
Provides-Extra: all
Provides-Extra: globals
Provides-Extra: graphics
Provides-Extra: ide
Provides-Extra: input
Provides-Extra: yaml
Requires-Dist: Pillow (>=11.0.0,<12.0.0) ; extra == "graphics" or extra == "all"
Requires-Dist: PySide6 (>=6.6,<7.0) ; extra == "ide" or extra == "all"
Requires-Dist: certifi (>=2024.7.4,<2025.0.0)
Requires-Dist: cryptography (>=44.0.1,<45.0.0)
Requires-Dist: idna (>=3.7,<4.0)
Requires-Dist: pygithub (>=2.5.0,<3.0.0) ; extra == "globals" or extra == "all"
Requires-Dist: pynput (>=1.7.7,<2.0.0) ; extra == "input" or extra == "all"
Requires-Dist: pyyaml (>=6.0,<7.0) ; extra == "yaml" or extra == "all"
Requires-Dist: requests (>=2.32.4,<3.0.0)
Requires-Dist: urllib3 (>=2.5.0,<3.0.0)
Project-URL: Documentation, https://github.com/James-HoneyBadger/GulfOfMexico/blob/main/DOCUMENTATION.md
Project-URL: Homepage, https://github.com/James-HoneyBadger/GulfOfMexico
Project-URL: Repository, https://github.com/James-HoneyBadger/GulfOfMexico
